{"place":{"name":"city/gatineau","loc":"45.47,-75.70"},"weather":{"time":"2023-12-14T14:09:54-0500","cond":"Mostly Cloudy","hum":62,"temp":{"absolute":2,"feels_like":-3},"prec":{"rain":0,"snow":0},"uv":0,"wind":"18@210"},"forecast":[{"time":"2023-12-14T15:00:00-0500","cond":"Mostly Cloudy","hum":63,"temp":{"absolute":2,"feels_like":-3},"prec":{"chance":1,"type":"precip","rain":0,"snow":0},"uv":0,"wind":"16@213"},{"time":"2023-12-14T16:00:00-0500","cond":"Partly Cloudy","hum":64,"temp":{"absolute":1,"feels_like":-3},"prec":{"chance":1,"type":"precip","rain":0,"snow":0},"uv":0,"wind":"15@218"},{"time":"2023-12-14T17:00:00-0500","cond":"Partly Cloudy","hum":68,"temp":{"absolute":1,"feels_like":-3},"prec":{"chance":2,"type":"precip","rain":0,"snow":0},"uv":0,"wind":"14@223"},{"time":"2023-12-14T18:00:00-0500","cond":"Partly Cloudy","hum":74,"temp":{"absolute":0,"feels_like":-5},"prec":{"chance":2,"type":"precip","rain":0,"snow":0},"uv":0,"wind":"15@225"},{"time":"2023-12-14T19:00:00-0500","cond":"Partly Cloudy","hum":77,"temp":{"absolute":0,"feels_like":-5},"prec":{"chance":2,"type":"precip","rain":0,"snow":0},"uv":0,"wind":"14@228"},{"time":"2023-12-14T20:00:00-0500","cond":"Partly Cloudy","hum":78,"temp":{"absolute":-1,"feels_like":-5},"prec":{"chance":3,"type":"precip","rain":0,"snow":0},"uv":0,"wind":"13@229"},{"time":"2023-12-14T21:00:00-0500","cond":"Partly Cloudy","hum":80,"temp":{"absolute":0,"feels_like":-4},"prec":{"chance":7,"type":"precip","rain":0,"snow":0},"uv":0,"wind":"12@226"},{"time":"2023-12-14T22:00:00-0500","cond":"Partly Cloudy","hum":79,"temp":{"absolute":0,"feels_like":-5},"prec":{"chance":11,"type":"precip","rain":0,"snow":0},"uv":0,"wind":"14@222"},{"time":"2023-12-14T23:00:00-0500","cond":"Partly Cloudy","hum":81,"temp":{"absolute":0,"feels_like":-5},"prec":{"chance":11,"type":"precip","rain":0,"snow":0},"uv":0,"wind":"14@221"},{"time":"2023-12-15T00:00:00-0500","cond":"Clear","hum":81,"temp":{"absolute":0,"feels_like":-5},"prec":{"chance":11,"type":"precip","rain":0,"snow":0},"uv":0,"wind":"15@219"},{"time":"2023-12-15T01:00:00-0500","cond":"Clear","hum":84,"temp":{"absolute":0,"feels_like":-5},"prec":{"chance":11,"type":"precip","rain":0,"snow":0},"uv":0,"wind":"15@222"},{"time":"2023-12-15T02:00:00-0500","cond":"Clear","hum":84,"temp":{"absolute":0,"feels_like":-4},"prec":{"chance":12,"type":"precip","rain":0,"snow":0},"uv":0,"wind":"14@221"},{"time":"2023-12-15T03:00:00-0500","cond":"Clear","hum":86,"temp":{"absolute":0,"feels_like":-4},"prec":{"chance":12,"type":"precip","rain":0,"snow":0},"uv":0,"wind":"14@227"},{"time":"2023-12-15T04:00:00-0500","cond":"Mostly Clear","hum":89,"temp":{"absolute":0,"feels_like":-4},"prec":{"chance":14,"type":"precip","rain":0,"snow":0},"uv":0,"wind":"13@226"},{"time":"2023-12-15T05:00:00-0500","cond":"Mostly Clear","hum":90,"temp":{"absolute":0,"feels_like":-4},"prec":{"chance":14,"type":"precip","rain":0,"snow":0},"uv":0,"wind":"12@225"},{"time":"2023-12-15T06:00:00-0500","cond":"Partly Cloudy","hum":91,"temp":{"absolute":0,"feels_like":-4},"prec":{"chance":14,"type":"precip","rain":0,"snow":0},"uv":0,"wind":"13@226"},{"time":"2023-12-15T07:00:00-0500","cond":"Partly Cloudy","hum":91,"temp":{"absolute":0,"feels_like":-4},"prec":{"chance":14,"type":"precip","rain":0,"snow":0},"uv":0,"wind":"14@231"},{"time":"2023-12-15T08:00:00-0500","cond":"Partly Cloudy","hum":90,"temp":{"absolute":1,"feels_like":-3},"prec":{"chance":14,"type":"precip","rain":0,"snow":0},"uv":0,"wind":"13@231"},{"time":"2023-12-15T09:00:00-0500","cond":"Partly Cloudy","hum":91,"temp":{"absolute":2,"feels_like":-2},"prec":{"chance":14,"type":"precip","rain":0,"snow":0},"uv":0,"wind":"13@233"},{"time":"2023-12-15T10:00:00-0500","cond":"Partly Cloudy","hum":87,"temp":{"absolute":4,"feels_like":0},"prec":{"chance":12,"type":"precip","rain":0,"snow":0},"uv":1,"wind":"15@238"},{"time":"2023-12-15T11:00:00-0500","cond":"Partly Cloudy","hum":81,"temp":{"absolute":5,"feels_like":2},"prec":{"chance":11,"type":"rain","rain":0,"snow":0},"uv":1,"wind":"16@243"},{"time":"2023-12-15T12:00:00-0500","cond":"Partly Cloudy","hum":79,"temp":{"absolute":6,"feels_like":3},"prec":{"chance":9,"type":"rain","rain":0,"snow":0},"uv":1,"wind":"17@252"},{"time":"2023-12-15T13:00:00-0500","cond":"Partly Cloudy","hum":74,"temp":{"absolute":7,"feels_like":4},"prec":{"chance":9,"type":"rain","rain":0,"snow":0},"uv":1,"wind":"17@255"},{"time":"2023-12-15T14:00:00-0500","cond":"Partly Cloudy","hum":74,"temp":{"absolute":7,"feels_like":4},"prec":{"chance":9,"type":"rain","rain":0,"snow":0},"uv":0,"wind":"16@257"},{"time":"2023-12-15T15:00:00-0500","cond":"Partly Cloudy","hum":76,"temp":{"absolute":6,"feels_like":4},"prec":{"chance":9,"type":"rain","rain":0,"snow":0},"uv":0,"wind":"14@255"},{"time":"2023-12-15T16:00:00-0500","cond":"Partly Cloudy","hum":82,"temp":{"absolute":5,"feels_like":2},"prec":{"chance":11,"type":"rain","rain":0,"snow":0},"uv":0,"wind":"13@258"},{"time":"2023-12-15T17:00:00-0500","cond":"Partly Cloudy","hum":85,"temp":{"absolute":4,"feels_like":1},"prec":{"chance":12,"type":"precip","rain":0,"snow":0},"uv":0,"wind":"11@263"},{"time":"2023-12-15T18:00:00-0500","cond":"Mostly Cloudy","hum":85,"temp":{"absolute":4,"feels_like":1},"prec":{"chance":12,"type":"precip","rain":0,"snow":0},"uv":0,"wind":"11@274"},{"time":"2023-12-15T19:00:00-0500","cond":"Cloudy","hum":87,"temp":{"absolute":4,"feels_like":1},"prec":{"chance":12,"type":"precip","rain":0,"snow":0},"uv":0,"wind":"10@274"},{"time":"2023-12-15T20:00:00-0500","cond":"Cloudy","hum":85,"temp":{"absolute":3,"feels_like":1},"prec":{"chance":14,"type":"precip","rain":0,"snow":0},"uv":0,"wind":"10@274"},{"time":"2023-12-15T21:00:00-0500","cond":"Cloudy","hum":87,"temp":{"absolute":3,"feels_like":0},"prec":{"chance":14,"type":"precip","rain":0,"snow":0},"uv":0,"wind":"11@274"},{"time":"2023-12-15T22:00:00-0500","cond":"Cloudy","hum":87,"temp":{"absolute":3,"feels_like":0},"prec":{"chance":14,"type":"precip","rain":0,"snow":0},"uv":0,"wind":"11@272"},{"time":"2023-12-15T23:00:00-0500","cond":"Cloudy","hum":89,"temp":{"absolute":3,"feels_like":0},"prec":{"chance":14,"type":"precip","rain":0,"snow":0},"uv":0,"wind":"11@280"},{"time":"2023-12-16T00:00:00-0500","cond":"Cloudy","hum":89,"temp":{"absolute":3,"feels_like":-1},"prec":{"chance":14,"type":"precip","rain":0,"snow":0},"uv":0,"wind":"11@288"},{"time":"2023-12-16T01:00:00-0500","cond":"Cloudy","hum":90,"temp":{"absolute":2,"feels_like":-1},"prec":{"chance":14,"type":"precip","rain":0,"snow":0},"uv":0,"wind":"11@295"},{"time":"2023-12-16T02:00:00-0500","cond":"Cloudy","hum":90,"temp":{"absolute":2,"feels_like":-1},"prec":{"chance":14,"type":"precip","rain":0,"snow":0},"uv":0,"wind":"10@301"},{"time":"2023-12-16T03:00:00-0500","cond":"Mostly Cloudy","hum":90,"temp":{"absolute":1,"feels_like":-2},"prec":{"chance":14,"type":"precip","rain":0,"snow":0},"uv":0,"wind":"10@316"},{"time":"2023-12-16T04:00:00-0500","cond":"Mostly Cloudy","hum":88,"temp":{"absolute":1,"feels_like":-2},"prec":{"chance":14,"type":"precip","rain":0,"snow":0},"uv":0,"wind":"10@334"},{"time":"2023-12-16T05:00:00-0500","cond":"Mostly Cloudy","hum":86,"temp":{"absolute":1,"feels_like":-3},"prec":{"chance":12,"type":"precip","rain":0,"snow":0},"uv":0,"wind":"10@345"},{"time":"2023-12-16T06:00:00-0500","cond":"Mostly Cloudy","hum":84,"temp":{"absolute":0,"feels_like":-3},"prec":{"chance":11,"type":"precip","rain":0,"snow":0},"uv":0,"wind":"10@355"},{"time":"2023-12-16T07:00:00-0500","cond":"Mostly Cloudy","hum":81,"temp":{"absolute":-1,"feels_like":-4},"prec":{"chance":11,"type":"precip","rain":0,"snow":0},"uv":0,"wind":"10@356"},{"time":"2023-12-16T08:00:00-0500","cond":"Mostly Cloudy","hum":78,"temp":{"absolute":-1,"feels_like":-4},"prec":{"chance":9,"type":"precip","rain":0,"snow":0},"uv":0,"wind":"9@7"},{"time":"2023-12-16T09:00:00-0500","cond":"Mostly Cloudy","hum":77,"temp":{"absolute":-1,"feels_like":-4},"prec":{"chance":9,"type":"precip","rain":0,"snow":0},"uv":0,"wind":"10@18"},{"time":"2023-12-16T10:00:00-0500","cond":"Mostly Cloudy","hum":72,"temp":{"absolute":0,"feels_like":-3},"prec":{"chance":7,"type":"precip","rain":0,"snow":0},"uv":0,"wind":"11@30"},{"time":"2023-12-16T11:00:00-0500","cond":"Mostly Cloudy","hum":68,"temp":{"absolute":1,"feels_like":-3},"prec":{"chance":5,"type":"precip","rain":0,"snow":0},"uv":1,"wind":"12@48"},{"time":"2023-12-16T12:00:00-0500","cond":"Mostly Cloudy","hum":67,"temp":{"absolute":1,"feels_like":-3},"prec":{"chance":4,"type":"precip","rain":0,"snow":0},"uv":1,"wind":"11@59"},{"time":"2023-12-16T13:00:00-0500","cond":"Mostly Cloudy","hum":63,"temp":{"absolute":1,"feels_like":-3},"prec":{"chance":4,"type":"precip","rain":0,"snow":0},"uv":1,"wind":"12@75"},{"time":"2023-12-16T14:00:00-0500","cond":"Mostly Cloudy","hum":64,"temp":{"absolute":1,"feels_like":-3},"prec":{"chance":4,"type":"precip","rain":0,"snow":0},"uv":0,"wind":"13@84"},{"time":"2023-12-16T15:00:00-0500","cond":"Mostly Cloudy","hum":67,"temp":{"absolute":1,"feels_like":-3},"prec":{"chance":5,"type":"precip","rain":0,"snow":0},"uv":0,"wind":"12@92"},{"time":"2023-12-16T16:00:00-0500","cond":"Mostly Cloudy","hum":70,"temp":{"absolute":0,"feels_like":-4},"prec":{"chance":7,"type":"precip","rain":0,"snow":0},"uv":0,"wind":"12@92"},{"time":"2023-12-16T17:00:00-0500","cond":"Mostly Cloudy","hum":75,"temp":{"absolute":-1,"feels_like":-5},"prec":{"chance":9,"type":"precip","rain":0,"snow":0},"uv":0,"wind":"12@90"},{"time":"2023-12-16T18:00:00-0500","cond":"Cloudy","hum":77,"temp":{"absolute":-1,"feels_like":-6},"prec":{"chance":9,"type":"precip","rain":0,"snow":0},"uv":0,"wind":"12@86"},{"time":"2023-12-16T19:00:00-0500","cond":"Mostly Cloudy","hum":77,"temp":{"absolute":-2,"feels_like":-6},"prec":{"chance":9,"type":"precip","rain":0,"snow":0},"uv":0,"wind":"12@86"},{"time":"2023-12-16T20:00:00-0500","cond":"Mostly Cloudy","hum":79,"temp":{"absolute":-2,"feels_like":-7},"prec":{"chance":9,"type":"precip","rain":0,"snow":0},"uv":0,"wind":"13@85"},{"time":"2023-12-16T21:00:00-0500","cond":"Cloudy","hum":79,"temp":{"absolute":-2,"feels_like":-7},"prec":{"chance":9,"type":"precip","rain":0,"snow":0},"uv":0,"wind":"12@86"},{"time":"2023-12-16T22:00:00-0500","cond":"Cloudy","hum":80,"temp":{"absolute":-2,"feels_like":-7},"prec":{"chance":9,"type":"precip","rain":0,"snow":0},"uv":0,"wind":"12@87"},{"time":"2023-12-16T23:00:00-0500","cond":"Cloudy","hum":82,"temp":{"absolute":-2,"feels_like":-7},"prec":{"chance":9,"type":"precip","rain":0,"snow":0},"uv":0,"wind":"13@87"},{"time":"2023-12-17T00:00:00-0500","cond":"Cloudy","hum":84,"temp":{"absolute":-2,"feels_like":-7},"prec":{"chance":9,"type":"precip","rain":0,"snow":0},"uv":0,"wind":"13@92"},{"time":"2023-12-17T01:00:00-0500","cond":"Cloudy","hum":83,"temp":{"absolute":-2,"feels_like":-6},"prec":{"chance":11,"type":"precip","rain":0,"snow":0},"uv":0,"wind":"12@91"},{"time":"2023-12-17T02:00:00-0500","cond":"Cloudy","hum":84,"temp":{"absolute":-2,"feels_like":-6},"prec":{"chance":11,"type":"precip","rain":0,"snow":0},"uv":0,"wind":"12@95"},{"time":"2023-12-17T03:00:00-0500","cond":"Cloudy","hum":85,"temp":{"absolute":-1,"feels_like":-5},"prec":{"chance":11,"type":"precip","rain":0,"snow":0},"uv":0,"wind":"12@97"},{"time":"2023-12-17T04:00:00-0500","cond":"Cloudy","hum":86,"temp":{"absolute":-1,"feels_like":-5},"prec":{"chance":16,"type":"precip","rain":0,"snow":0},"uv":0,"wind":"12@99"},{"time":"2023-12-17T05:00:00-0500","cond":"Cloudy","hum":87,"temp":{"absolute":0,"feels_like":-4},"prec":{"chance":18,"type":"precip","rain":0,"snow":0},"uv":0,"wind":"11@110"},{"time":"2023-12-17T06:00:00-0500","cond":"Cloudy","hum":87,"temp":{"absolute":0,"feels_like":-4},"prec":{"chance":18,"type":"precip","rain":0,"snow":0},"uv":0,"wind":"12@115"},{"time":"2023-12-17T07:00:00-0500","cond":"Cloudy","hum":89,"temp":{"absolute":1,"feels_like":-3},"prec":{"chance":23,"type":"precip","rain":0,"snow":0},"uv":0,"wind":"11@124"},{"time":"2023-12-17T08:00:00-0500","cond":"Cloudy","hum":87,"temp":{"absolute":2,"feels_like":-2},"prec":{"chance":23,"type":"precip","rain":0,"snow":0},"uv":0,"wind":"11@131"},{"time":"2023-12-17T09:00:00-0500","cond":"Cloudy","hum":85,"temp":{"absolute":2,"feels_like":-1},"prec":{"chance":23,"type":"precip","rain":0,"snow":0},"uv":0,"wind":"12@143"},{"time":"2023-12-17T10:00:00-0500","cond":"Cloudy","hum":84,"temp":{"absolute":3,"feels_like":0},"prec":{"chance":24,"type":"precip","rain":0,"snow":0},"uv":0,"wind":"14@156"},{"time":"2023-12-17T11:00:00-0500","cond":"Cloudy","hum":83,"temp":{"absolute":4,"feels_like":1},"prec":{"chance":24,"type":"precip","rain":0,"snow":0},"uv":0,"wind":"15@165"},{"time":"2023-12-17T12:00:00-0500","cond":"Cloudy","hum":83,"temp":{"absolute":5,"feels_like":1},"prec":{"chance":24,"type":"rain","rain":0,"snow":0},"uv":0,"wind":"15@159"},{"time":"2023-12-17T13:00:00-0500","cond":"Showers","hum":81,"temp":{"absolute":5,"feels_like":2},"prec":{"chance":39,"type":"rain","rain":0.1,"snow":0},"uv":0,"wind":"15@158"},{"time":"2023-12-17T14:00:00-0500","cond":"Light Rain","hum":81,"temp":{"absolute":5,"feels_like":2},"prec":{"chance":85,"type":"rain","rain":0.1,"snow":0},"uv":0,"wind":"14@152"}]}