{"place":{"name":"park/mauricie","loc":"45.442,-71.133"},"weather":{"time":"2023-11-20T13:17:33-0500","cond":"Mostly Cloudy","hum":76,"temp":{"absolute":-8,"feels_like":-15},"prec":{"rain":0,"snow":0},"uv":1,"wind":"21@300"},"forecast":[{"time":"2023-11-20T14:00:00-0500","cond":"Partly Cloudy","hum":70,"temp":{"absolute":-7,"feels_like":-15},"prec":{"chance":1,"type":"snow","rain":0,"snow":0},"uv":1,"wind":"20@307"},{"time":"2023-11-20T15:00:00-0500","cond":"Partly Cloudy","hum":69,"temp":{"absolute":-7,"feels_like":-14},"prec":{"chance":1,"type":"snow","rain":0,"snow":0},"uv":0,"wind":"18@306"},{"time":"2023-11-20T16:00:00-0500","cond":"Mostly Sunny","hum":70,"temp":{"absolute":-8,"feels_like":-14},"prec":{"chance":1,"type":"snow","rain":0,"snow":0},"uv":0,"wind":"15@304"},{"time":"2023-11-20T17:00:00-0500","cond":"Clear","hum":68,"temp":{"absolute":-9,"feels_like":-14},"prec":{"chance":1,"type":"snow","rain":0,"snow":0},"uv":0,"wind":"13@300"},{"time":"2023-11-20T18:00:00-0500","cond":"Clear","hum":70,"temp":{"absolute":-9,"feels_like":-15},"prec":{"chance":2,"type":"snow","rain":0,"snow":0},"uv":0,"wind":"12@294"},{"time":"2023-11-20T19:00:00-0500","cond":"Clear","hum":74,"temp":{"absolute":-9,"feels_like":-15},"prec":{"chance":2,"type":"snow","rain":0,"snow":0},"uv":0,"wind":"11@290"},{"time":"2023-11-20T20:00:00-0500","cond":"Clear","hum":74,"temp":{"absolute":-10,"feels_like":-15},"prec":{"chance":5,"type":"snow","rain":0,"snow":0},"uv":0,"wind":"10@280"},{"time":"2023-11-20T21:00:00-0500","cond":"Clear","hum":77,"temp":{"absolute":-10,"feels_like":-15},"prec":{"chance":9,"type":"snow","rain":0,"snow":0},"uv":0,"wind":"9@273"},{"time":"2023-11-20T22:00:00-0500","cond":"Clear","hum":79,"temp":{"absolute":-10,"feels_like":-14},"prec":{"chance":9,"type":"snow","rain":0,"snow":0},"uv":0,"wind":"7@261"},{"time":"2023-11-20T23:00:00-0500","cond":"Clear","hum":81,"temp":{"absolute":-11,"feels_like":-14},"prec":{"chance":11,"type":"snow","rain":0,"snow":0},"uv":0,"wind":"6@255"},{"time":"2023-11-21T00:00:00-0500","cond":"Clear","hum":83,"temp":{"absolute":-11,"feels_like":-14},"prec":{"chance":11,"type":"snow","rain":0,"snow":0},"uv":0,"wind":"5@230"},{"time":"2023-11-21T01:00:00-0500","cond":"Clear","hum":83,"temp":{"absolute":-11,"feels_like":-14},"prec":{"chance":11,"type":"snow","rain":0,"snow":0},"uv":0,"wind":"5@227"},{"time":"2023-11-21T02:00:00-0500","cond":"Clear","hum":82,"temp":{"absolute":-11,"feels_like":-14},"prec":{"chance":11,"type":"snow","rain":0,"snow":0},"uv":0,"wind":"5@240"},{"time":"2023-11-21T03:00:00-0500","cond":"Clear","hum":84,"temp":{"absolute":-11,"feels_like":-11},"prec":{"chance":11,"type":"snow","rain":0,"snow":0},"uv":0,"wind":"4@238"},{"time":"2023-11-21T04:00:00-0500","cond":"Clear","hum":84,"temp":{"absolute":-11,"feels_like":-11},"prec":{"chance":11,"type":"snow","rain":0,"snow":0},"uv":0,"wind":"3@214"},{"time":"2023-11-21T05:00:00-0500","cond":"Clear","hum":86,"temp":{"absolute":-12,"feels_like":-12},"prec":{"chance":11,"type":"snow","rain":0,"snow":0},"uv":0,"wind":"3@185"},{"time":"2023-11-21T06:00:00-0500","cond":"Clear","hum":85,"temp":{"absolute":-12,"feels_like":-12},"prec":{"chance":11,"type":"snow","rain":0,"snow":0},"uv":0,"wind":"2@169"},{"time":"2023-11-21T07:00:00-0500","cond":"Sunny","hum":83,"temp":{"absolute":-12,"feels_like":-12},"prec":{"chance":9,"type":"snow","rain":0,"snow":0},"uv":0,"wind":"2@139"},{"time":"2023-11-21T08:00:00-0500","cond":"Sunny","hum":79,"temp":{"absolute":-11,"feels_like":-11},"prec":{"chance":5,"type":"snow","rain":0,"snow":0},"uv":0,"wind":"3@119"},{"time":"2023-11-21T09:00:00-0500","cond":"Sunny","hum":67,"temp":{"absolute":-9,"feels_like":-9},"prec":{"chance":2,"type":"snow","rain":0,"snow":0},"uv":1,"wind":"3@118"},{"time":"2023-11-21T10:00:00-0500","cond":"Sunny","hum":54,"temp":{"absolute":-7,"feels_like":-7},"prec":{"chance":0,"type":"snow","rain":0,"snow":0},"uv":1,"wind":"5@107"},{"time":"2023-11-21T11:00:00-0500","cond":"Sunny","hum":45,"temp":{"absolute":-5,"feels_like":-8},"prec":{"chance":0,"type":"snow","rain":0,"snow":0},"uv":1,"wind":"6@117"},{"time":"2023-11-21T12:00:00-0500","cond":"Mostly Sunny","hum":40,"temp":{"absolute":-3,"feels_like":-7},"prec":{"chance":0,"type":"precip","rain":0,"snow":0},"uv":1,"wind":"8@140"},{"time":"2023-11-21T13:00:00-0500","cond":"Mostly Sunny","hum":36,"temp":{"absolute":-3,"feels_like":-6},"prec":{"chance":0,"type":"precip","rain":0,"snow":0},"uv":1,"wind":"10@154"},{"time":"2023-11-21T14:00:00-0500","cond":"Partly Cloudy","hum":36,"temp":{"absolute":-3,"feels_like":-6},"prec":{"chance":0,"type":"precip","rain":0,"snow":0},"uv":1,"wind":"10@146"},{"time":"2023-11-21T15:00:00-0500","cond":"Mostly Cloudy","hum":40,"temp":{"absolute":-3,"feels_like":-7},"prec":{"chance":0,"type":"precip","rain":0,"snow":0},"uv":0,"wind":"10@145"},{"time":"2023-11-21T16:00:00-0500","cond":"Mostly Cloudy","hum":47,"temp":{"absolute":-5,"feels_like":-8},"prec":{"chance":0,"type":"snow","rain":0,"snow":0},"uv":0,"wind":"9@140"},{"time":"2023-11-21T17:00:00-0500","cond":"Mostly Cloudy","hum":50,"temp":{"absolute":-5,"feels_like":-9},"prec":{"chance":0,"type":"snow","rain":0,"snow":0},"uv":0,"wind":"10@133"},{"time":"2023-11-21T18:00:00-0500","cond":"Cloudy","hum":49,"temp":{"absolute":-5,"feels_like":-10},"prec":{"chance":0,"type":"snow","rain":0,"snow":0},"uv":0,"wind":"12@143"},{"time":"2023-11-21T19:00:00-0500","cond":"Cloudy","hum":51,"temp":{"absolute":-6,"feels_like":-11},"prec":{"chance":0,"type":"snow","rain":0,"snow":0},"uv":0,"wind":"12@146"},{"time":"2023-11-21T20:00:00-0500","cond":"Cloudy","hum":50,"temp":{"absolute":-5,"feels_like":-11},"prec":{"chance":4,"type":"snow","rain":0,"snow":0},"uv":0,"wind":"13@151"},{"time":"2023-11-21T21:00:00-0500","cond":"Cloudy","hum":50,"temp":{"absolute":-5,"feels_like":-10},"prec":{"chance":0,"type":"snow","rain":0,"snow":0},"uv":0,"wind":"15@153"},{"time":"2023-11-21T22:00:00-0500","cond":"Cloudy","hum":54,"temp":{"absolute":-5,"feels_like":-10},"prec":{"chance":24,"type":"snow","rain":0,"snow":0},"uv":0,"wind":"15@153"},{"time":"2023-11-21T23:00:00-0500","cond":"Snow Showers","hum":63,"temp":{"absolute":-5,"feels_like":-11},"prec":{"chance":49,"type":"snow","rain":0.2,"snow":0.2},"uv":0,"wind":"16@153"},{"time":"2023-11-22T00:00:00-0500","cond":"Snow","hum":68,"temp":{"absolute":-4,"feels_like":-10},"prec":{"chance":78,"type":"snow","rain":0.43,"snow":0.5},"uv":0,"wind":"16@153"},{"time":"2023-11-22T01:00:00-0500","cond":"Snow","hum":74,"temp":{"absolute":-4,"feels_like":-10},"prec":{"chance":93,"type":"snow","rain":1,"snow":1.1},"uv":0,"wind":"18@150"},{"time":"2023-11-22T02:00:00-0500","cond":"Snow","hum":81,"temp":{"absolute":-4,"feels_like":-10},"prec":{"chance":97,"type":"snow","rain":1.35,"snow":1.4},"uv":0,"wind":"20@152"},{"time":"2023-11-22T03:00:00-0500","cond":"Snow","hum":84,"temp":{"absolute":-4,"feels_like":-10},"prec":{"chance":96,"type":"snow","rain":1.35,"snow":1.4},"uv":0,"wind":"20@150"},{"time":"2023-11-22T04:00:00-0500","cond":"Snow","hum":86,"temp":{"absolute":-3,"feels_like":-9},"prec":{"chance":98,"type":"snow","rain":1.35,"snow":1.4},"uv":0,"wind":"21@151"},{"time":"2023-11-22T05:00:00-0500","cond":"Snow","hum":87,"temp":{"absolute":-3,"feels_like":-9},"prec":{"chance":96,"type":"snow","rain":1.02,"snow":1},"uv":0,"wind":"22@151"},{"time":"2023-11-22T06:00:00-0500","cond":"Snow","hum":86,"temp":{"absolute":-3,"feels_like":-9},"prec":{"chance":94,"type":"snow","rain":0.82,"snow":0.8},"uv":0,"wind":"21@151"},{"time":"2023-11-22T07:00:00-0500","cond":"Snow","hum":87,"temp":{"absolute":-2,"feels_like":-8},"prec":{"chance":89,"type":"snow","rain":0.6,"snow":0.6},"uv":0,"wind":"20@152"},{"time":"2023-11-22T08:00:00-0500","cond":"Snow","hum":87,"temp":{"absolute":-2,"feels_like":-8},"prec":{"chance":87,"type":"snow","rain":0.7,"snow":0.7},"uv":0,"wind":"21@149"},{"time":"2023-11-22T09:00:00-0500","cond":"Snow","hum":88,"temp":{"absolute":-1,"feels_like":-7},"prec":{"chance":93,"type":"snow","rain":1.05,"snow":1},"uv":0,"wind":"19@151"},{"time":"2023-11-22T10:00:00-0500","cond":"Snow","hum":90,"temp":{"absolute":-1,"feels_like":-6},"prec":{"chance":93,"type":"snow","rain":0.85,"snow":0.8},"uv":0,"wind":"20@150"},{"time":"2023-11-22T11:00:00-0500","cond":"Snow","hum":90,"temp":{"absolute":-1,"feels_like":-6},"prec":{"chance":92,"type":"snow","rain":0.75,"snow":0.7},"uv":1,"wind":"18@152"},{"time":"2023-11-22T12:00:00-0500","cond":"Snow","hum":92,"temp":{"absolute":-1,"feels_like":-6},"prec":{"chance":88,"type":"snow","rain":0.72,"snow":0.7},"uv":1,"wind":"18@148"},{"time":"2023-11-22T13:00:00-0500","cond":"Snow","hum":92,"temp":{"absolute":-1,"feels_like":-6},"prec":{"chance":83,"type":"snow","rain":0.42,"snow":0.4},"uv":0,"wind":"19@147"},{"time":"2023-11-22T14:00:00-0500","cond":"Light Snow","hum":91,"temp":{"absolute":0,"feels_like":-5},"prec":{"chance":80,"type":"snow","rain":0.3,"snow":0.3},"uv":0,"wind":"17@141"},{"time":"2023-11-22T15:00:00-0500","cond":"Light Snow","hum":90,"temp":{"absolute":0,"feels_like":-5},"prec":{"chance":74,"type":"snow","rain":0.2,"snow":0.2},"uv":0,"wind":"16@137"},{"time":"2023-11-22T16:00:00-0500","cond":"Snow Showers","hum":90,"temp":{"absolute":0,"feels_like":-4},"prec":{"chance":60,"type":"snow","rain":0.1,"snow":0.1},"uv":0,"wind":"13@127"},{"time":"2023-11-22T17:00:00-0500","cond":"Showers","hum":86,"temp":{"absolute":1,"feels_like":-3},"prec":{"chance":51,"type":"rain","rain":0.1,"snow":0},"uv":0,"wind":"13@117"},{"time":"2023-11-22T18:00:00-0500","cond":"Showers","hum":86,"temp":{"absolute":1,"feels_like":-3},"prec":{"chance":54,"type":"rain","rain":0.1,"snow":0},"uv":0,"wind":"13@116"},{"time":"2023-11-22T19:00:00-0500","cond":"Snow Showers","hum":90,"temp":{"absolute":0,"feels_like":-4},"prec":{"chance":44,"type":"snow","rain":0.1,"snow":0.1},"uv":0,"wind":"12@113"},{"time":"2023-11-22T20:00:00-0500","cond":"Snow Showers","hum":92,"temp":{"absolute":0,"feels_like":-4},"prec":{"chance":44,"type":"snow","rain":0.1,"snow":0.1},"uv":0,"wind":"11@110"},{"time":"2023-11-22T21:00:00-0500","cond":"Snow Showers","hum":93,"temp":{"absolute":0,"feels_like":-3},"prec":{"chance":44,"type":"snow","rain":0.1,"snow":0.1},"uv":0,"wind":"9@108"},{"time":"2023-11-22T22:00:00-0500","cond":"Snow Showers","hum":94,"temp":{"absolute":0,"feels_like":-3},"prec":{"chance":44,"type":"snow","rain":0.07,"snow":0.1},"uv":0,"wind":"7@91"},{"time":"2023-11-22T23:00:00-0500","cond":"Snow Showers","hum":94,"temp":{"absolute":-1,"feels_like":-3},"prec":{"chance":44,"type":"snow","rain":0.1,"snow":0.1},"uv":0,"wind":"6@62"},{"time":"2023-11-23T00:00:00-0500","cond":"Snow Showers","hum":94,"temp":{"absolute":-1,"feels_like":-2},"prec":{"chance":44,"type":"snow","rain":0.1,"snow":0.1},"uv":0,"wind":"5@53"},{"time":"2023-11-23T01:00:00-0500","cond":"Snow Showers","hum":97,"temp":{"absolute":-1,"feels_like":-1},"prec":{"chance":39,"type":"snow","rain":0,"snow":0},"uv":0,"wind":"5@0"},{"time":"2023-11-23T02:00:00-0500","cond":"Snow Showers","hum":96,"temp":{"absolute":-1,"feels_like":-3},"prec":{"chance":39,"type":"snow","rain":0,"snow":0},"uv":0,"wind":"6@311"},{"time":"2023-11-23T03:00:00-0500","cond":"Snow Showers","hum":96,"temp":{"absolute":-1,"feels_like":-3},"prec":{"chance":39,"type":"snow","rain":0,"snow":0},"uv":0,"wind":"6@308"},{"time":"2023-11-23T04:00:00-0500","cond":"Snow Showers","hum":96,"temp":{"absolute":-1,"feels_like":-3},"prec":{"chance":39,"type":"snow","rain":0,"snow":0},"uv":0,"wind":"6@295"},{"time":"2023-11-23T05:00:00-0500","cond":"Snow Showers","hum":97,"temp":{"absolute":-1,"feels_like":-3},"prec":{"chance":39,"type":"snow","rain":0.08,"snow":0.1},"uv":0,"wind":"6@296"},{"time":"2023-11-23T06:00:00-0500","cond":"Snow Showers","hum":97,"temp":{"absolute":-2,"feels_like":-4},"prec":{"chance":40,"type":"snow","rain":0.08,"snow":0.1},"uv":0,"wind":"5@295"},{"time":"2023-11-23T07:00:00-0500","cond":"Snow Showers","hum":97,"temp":{"absolute":-2,"feels_like":-4},"prec":{"chance":44,"type":"snow","rain":0.1,"snow":0.1},"uv":0,"wind":"7@285"},{"time":"2023-11-23T08:00:00-0500","cond":"Snow Showers","hum":99,"temp":{"absolute":-2,"feels_like":-5},"prec":{"chance":53,"type":"snow","rain":0.1,"snow":0.1},"uv":0,"wind":"8@287"},{"time":"2023-11-23T09:00:00-0500","cond":"Snow Showers","hum":99,"temp":{"absolute":-2,"feels_like":-5},"prec":{"chance":44,"type":"snow","rain":0.1,"snow":0.1},"uv":0,"wind":"8@285"},{"time":"2023-11-23T10:00:00-0500","cond":"Snow Showers","hum":98,"temp":{"absolute":-2,"feels_like":-5},"prec":{"chance":49,"type":"snow","rain":0.1,"snow":0.1},"uv":0,"wind":"9@280"},{"time":"2023-11-23T11:00:00-0500","cond":"Snow Showers","hum":94,"temp":{"absolute":-2,"feels_like":-5},"prec":{"chance":54,"type":"snow","rain":0.1,"snow":0.1},"uv":1,"wind":"11@276"},{"time":"2023-11-23T12:00:00-0500","cond":"Snow Showers","hum":91,"temp":{"absolute":-2,"feels_like":-6},"prec":{"chance":44,"type":"snow","rain":0.1,"snow":0.1},"uv":1,"wind":"12@276"},{"time":"2023-11-23T13:00:00-0500","cond":"Snow Showers","hum":90,"temp":{"absolute":-2,"feels_like":-7},"prec":{"chance":46,"type":"snow","rain":0.1,"snow":0.1},"uv":0,"wind":"14@278"}]}